omnibench/__init__.py
omnibench/py.typed
omnibench/version.py
omnibench/core/__init__.py
omnibench/core/benchmarker.py
omnibench/core/types.py
omnibench/integrations/__init__.py
omnibench/integrations/pydantic_ai/__init__.py
omnibench/integrations/pydantic_ai/benchmarker.py
omnibench/logging/__init__.py
omnibench/logging/evaluator.py
omnibench/logging/logger.py
omnibench/logging/simple_ai_logger.py
omnibench/logging/visual_test_clean_print.py
omnibench/objectives/__init__.py
omnibench/objectives/base.py
omnibench/objectives/combined.py
omnibench/objectives/llm_judge.py
omnibench/objectives/output.py
omnibench/objectives/path.py
omnibench/objectives/state.py
omnibench/utils/__init__.py
omnibench-0.1.2.dist-info/licenses/LICENSE
omnibench-0.1.2.dist-info/METADATA
omnibench-0.1.2.dist-info/WHEEL
omnibench-0.1.2.dist-info/top_level.txt
omnibench-0.1.2.dist-info/RECORD
