Metadata-Version: 2.4
Name: omnibench
Version: 0.1.2
Summary: Comprehensive AI Agent Benchmarking Framework
Author-email: BrainGnosis <dev@braingnosis.dev>
Maintainer-email: BrainGnosis <dev@braingnosis.dev>
License-Expression: Apache-2.0
Project-URL: Homepage, https://github.com/BrainGnosis/OmniBench
Project-URL: Repository, https://github.com/BrainGnosis/OmniBench
Project-URL: Documentation, https://github.com/BrainGnosis/OmniBench#readme
Project-URL: Bug Tracker, https://github.com/BrainGnosis/OmniBench/issues
Keywords: ai,agent,benchmarking,evaluation,llm,testing,performance
Classifier: Development Status :: 4 - Beta
Classifier: Intended Audience :: Developers
Classifier: Intended Audience :: Science/Research
Classifier: Operating System :: OS Independent
Classifier: Programming Language :: Python :: 3
Classifier: Programming Language :: Python :: 3.10
Classifier: Programming Language :: Python :: 3.11
Classifier: Programming Language :: Python :: 3.12
Classifier: Topic :: Scientific/Engineering :: Artificial Intelligence
Classifier: Topic :: Software Development :: Testing
Classifier: Topic :: Software Development :: Quality Assurance
Requires-Python: >=3.10
License-File: LICENSE
Requires-Dist: langchain<0.4.0,>=0.3.20
Requires-Dist: langchain_core<0.4.0,>=0.3.70
Requires-Dist: langchain_openai<0.4.0,>=0.3.30
Requires-Dist: numpy<3.0.0,>=2.0.0
Requires-Dist: pydantic<3.0.0,>=2.10.0
Requires-Dist: rich<15.0.0,>=14.0.0
Requires-Dist: tqdm<5.0.0,>=4.60.0
Requires-Dist: typing-extensions>=4.0.0
Provides-Extra: llm
Requires-Dist: langchain<0.4.0,>=0.3.20; extra == "llm"
Requires-Dist: langchain-openai<0.4.0,>=0.3.30; extra == "llm"
Requires-Dist: langchain-core<0.4.0,>=0.3.70; extra == "llm"
Provides-Extra: dev
Requires-Dist: pytest>=7.0.0; extra == "dev"
Requires-Dist: pytest-cov>=4.0.0; extra == "dev"
Requires-Dist: pytest-asyncio>=0.21.0; extra == "dev"
Requires-Dist: black>=23.0.0; extra == "dev"
Requires-Dist: isort>=5.12.0; extra == "dev"
Requires-Dist: flake8>=6.0.0; extra == "dev"
Requires-Dist: mypy>=1.0.0; extra == "dev"
Requires-Dist: pre-commit>=3.0.0; extra == "dev"
Provides-Extra: docs
Requires-Dist: mkdocs>=1.5.0; extra == "docs"
Requires-Dist: mkdocs-material>=9.0.0; extra == "docs"
Requires-Dist: mkdocstrings[python]>=0.22.0; extra == "docs"
Provides-Extra: all
Requires-Dist: omnibench[dev,docs,llm]; extra == "all"
Dynamic: license-file
